{"output":"Para cada caso de teste imprima a string formatada de acordo com os regras de formatação.","input":"A entrada é composta por vários casos de teste. Cada caso de teste é composto por dois valores inteiros, dolares (0 ≤ dolares ≤ 2 * 109) e centavos (0 ≤ centavos ≤ 99), respectivamente.","level":3,"name":"Formatação Monetária","has_images":false,"description":"Frequentemente é necessário escrever valores monetários em um formato padrão.\n\n                    Decidimos a formatação de quantidades na seguinte forma: \n\n                       1. O montante deve começar com '$';\n                       2. A quantidade deve terminar com um ponto decimal e exatamente dois dígitos seguintes;\n                       3. Os dígitos à esquerda do ponto decimal devem ser separador em grupos de três por vírgulas.\n\n                \n                    Sua tarefa neste problema é criar um programa que, recebendo dois valores inteiros dólares e centavos retorne a String formatada corretamente.","id":"1309","category":"Matemática","statistics":{"level":"3 / 10","submissions":3905,"solved":1819,"ratio":"46.58%"}}