{"output":"Você deverá imprimir: \"Falta(m) X pomekon(s).\", onde X representa a quantidade Pomekons não capturados.","input":"A primeira linha do caso de teste consiste de um inteiro N (1 ≤ N ≤ 10³), representando a quantidade de Pomekons que Dabriel já capturou.\nAs próximas N linhas consistem de uma string S (1 ≤ |S| ≤ 10³), representando o nome de cada Pomekons. O nome de cada Pomekons consiste apenas de letras maiúsculas e minúsculas.","level":3,"name":"Coleção de Pomekon","has_images":false,"description":"Desde que foi lançado oficialmente o Pomekon no Brasil, Dabriel está tentando realizar seu maior sonho: Ser um Mestre Pomekon. Sua meta é conquistar os 151 Pomekons disponíveis. Ele já conseguiu capturar muitos monstrinhos, porém em sua cidade aparecem muitos Pomekons repetidos, fazendo com que ele capture diversas vezes o mesmo Pomekon.\n\nVendo que sua mochila está bem cheia, Dabriel pediu para que você fizesse um programa de computador que informasse a ele quantos Pomekons faltam para completar a coleção.","id":"2174","category":"Strings","statistics":{"level":"3 / 10","submissions":5720,"solved":2464,"ratio":"43.08%"}}