{"output":"Imprima uma linha contendo um inteiro representando quantas escadinhas existem na sequência.","input":"A primeira linha da entra contém um inteiro N (1 ≤ N ≤ 1000) indicando o tamanho da sequência de números. A segunda linha contém N inteiros definindo a sequência. O valor dos números da sequência está entre −106 e 106 inclusive.","level":3,"name":"Escadinha","has_images":false,"description":"Dizemos que uma sequência de números é uma escadinha, se a diferença entre números consecutivos é sempre a mesma. Por exemplo, \u201c2, 3, 4, 5\u201d e \u201c10, 7, 4\u201d são escadinhas. Note que qualquer sequência com apenas um ou dois números também é uma escadinha! Neste problema estamos procurando escadinhas em uma sequência maior de números. Dada uma sequência de números, queremos determinar quantas escadinhas existem. Mas só estamos interessados em escadinhas tão longas quanto possível. Por isso, se uma escadinha é um pedaço de outra, consideramos somente a maior. Por exemplo, na sequência \u201c1, 1, 1, 3, 5, 4, 8, 12\u201d temos 4 escadinhas diferentes: \u201c1, 1, 1\u201d, \u201c1, 3, 5\u201d, \u201c5, 4\u201d e \u201c4, 8, 12\u201d.","id":"2782","category":"Iniciante","statistics":{"level":"3 / 10","submissions":712,"solved":372,"ratio":"52.25%"}}